binalyze_air/__init__.py
binalyze_air/base.py
binalyze_air/client.py
binalyze_air/config.py
binalyze_air/exceptions.py
binalyze_air/http_client.py
binalyze_air/apis/__init__.py
binalyze_air/apis/acquisitions.py
binalyze_air/apis/api_tokens.py
binalyze_air/apis/assets.py
binalyze_air/apis/audit_logs.py
binalyze_air/apis/auth.py
binalyze_air/apis/auto_asset_tags.py
binalyze_air/apis/backup.py
binalyze_air/apis/baseline.py
binalyze_air/apis/cases.py
binalyze_air/apis/cloud_forensics.py
binalyze_air/apis/event_subscription.py
binalyze_air/apis/evidence.py
binalyze_air/apis/interact.py
binalyze_air/apis/investigation_hub.py
binalyze_air/apis/license.py
binalyze_air/apis/logger.py
binalyze_air/apis/multipart_upload.py
binalyze_air/apis/notifications.py
binalyze_air/apis/organizations.py
binalyze_air/apis/params.py
binalyze_air/apis/policies.py
binalyze_air/apis/preset_filters.py
binalyze_air/apis/recent_activities.py
binalyze_air/apis/relay_server.py
binalyze_air/apis/settings.py
binalyze_air/apis/tasks.py
binalyze_air/apis/triage.py
binalyze_air/apis/user_management.py
binalyze_air/apis/webhook_executions.py
binalyze_air/apis/webhooks.py
binalyze_air/commands/__init__.py
binalyze_air/commands/acquisitions.py
binalyze_air/commands/api_tokens.py
binalyze_air/commands/assets.py
binalyze_air/commands/auth.py
binalyze_air/commands/auto_asset_tags.py
binalyze_air/commands/backup.py
binalyze_air/commands/baseline.py
binalyze_air/commands/cases.py
binalyze_air/commands/cloud_forensics.py
binalyze_air/commands/event_subscription.py
binalyze_air/commands/evidences.py
binalyze_air/commands/interact.py
binalyze_air/commands/investigation_hub.py
binalyze_air/commands/license.py
binalyze_air/commands/logger.py
binalyze_air/commands/multipart_upload.py
binalyze_air/commands/notifications.py
binalyze_air/commands/organizations.py
binalyze_air/commands/policies.py
binalyze_air/commands/preset_filters.py
binalyze_air/commands/recent_activities.py
binalyze_air/commands/relay_server.py
binalyze_air_sdk-1.0.3.dist-info/METADATA
binalyze_air_sdk-1.0.3.dist-info/WHEEL
binalyze_air_sdk-1.0.3.dist-info/top_level.txt
binalyze_air_sdk-1.0.3.dist-info/RECORD
